breizorro/__init__.py
breizorro/breizorro.py
breizorro/breizorro.yaml
breizorro/catalog.py
breizorro/gui.py
breizorro/main.py
breizorro/utils.py
breizorro-0.2.0.dist-info/LICENSE
breizorro-0.2.0.dist-info/METADATA
breizorro-0.2.0.dist-info/WHEEL
breizorro-0.2.0.dist-info/entry_points.txt
breizorro-0.2.0.dist-info/RECORD
